HISTORY.txt
MANIFEST.in
README.rst
setup.py
ftw/__init__.py
ftw.recipe.solr.egg-info/PKG-INFO
ftw.recipe.solr.egg-info/SOURCES.txt
ftw.recipe.solr.egg-info/dependency_links.txt
ftw.recipe.solr.egg-info/entry_points.txt
ftw.recipe.solr.egg-info/namespace_packages.txt
ftw.recipe.solr.egg-info/not-zip-safe
ftw.recipe.solr.egg-info/requires.txt
ftw.recipe.solr.egg-info/top_level.txt
ftw/recipe/__init__.py
ftw/recipe/solr/README.txt
ftw/recipe/solr/__init__.py
ftw/recipe/solr/defaults.py
ftw/recipe/solr/tests.py
ftw/recipe/solr/utils.py
ftw/recipe/solr/conf/managed-schema
ftw/recipe/solr/conf/mapping-FoldToASCII.txt
ftw/recipe/solr/conf/solrconfig.xml
ftw/recipe/solr/conf/stopwords.txt
ftw/recipe/solr/conf/synonyms.txt
ftw/recipe/solr/conf/lang/de.txt
ftw/recipe/solr/templates/core.properties.tmpl
ftw/recipe/solr/templates/log4j2.xml.tmpl
ftw/recipe/solr/templates/solr.xml.tmpl
ftw/recipe/solr/templates/startup.tmpl
ftw/recipe/solr/templates/zoo.cfg.tmpl
ftw/recipe/solr/testdata/solr-7.2.1.tgz