Metadata-Version: 2.1
Name: ftw.recipe.solr
Version: 1.3.7
Summary: A zc.buildout recipe to install a Solr server
Home-page: https://github.com/4teamwork/ftw.recipe.solr
Author: 4teamwork AG
Author-email: mailto:info@4teamwork.ch
License: GPL2
Platform: UNKNOWN
Classifier: Framework :: Buildout :: Recipe
Classifier: Intended Audience :: Developers
Classifier: License :: OSI Approved :: Zope Public License
Classifier: Programming Language :: Python
Classifier: Topic :: Software Development :: Build Tools
Provides-Extra: tests
